{	
  "name": "Multi Press II",
  "description": "A tier 3 graphite press. Require Cryofluid as coolant.",
    "type": "GenericCrafter",
	"size": 4,
	"hasPower": true,
	"hasItems": true,
	"itemCapacity": 30,
	"craftTime": 30,
	"craftEffect": "pulverize",
	"updateEffect": "pulverizeSmall",
	"consumes": {
		"power": 6,
		"items": {
			"items": [
               "coal/10",             
 			]
		},
                   "liquid": {
			"liquid": "cryofluid",
			"amount": 0.4
		}
	},
	"requirements": [
        "lead/250",
        "graphite/150",
        "titanium/200",
        "silicon/100",
        "surge-alloy/20",
        "plastanium/50"
	],
	"category": "crafting",
	"research": "multi-press",
	"outputItem": "graphite/8"
}
